horpy/__init__.py
horpy/main.py
horpy/specials.py
horpy-0.1.0.dist-info/METADATA
horpy-0.1.0.dist-info/WHEEL
horpy-0.1.0.dist-info/RECORD
