Metadata-Version: 2.1
Name: horpy
Version: 0.1.0
Summary: Um pacote que plota gráficos 2D para a função radial do átomo de hidrogênio e 3D para a parte angular.
Author: Ramon Medeiro
Author-email: r.medeiro10@gmail.com
Requires-Python: >=3.10,<3.12
Classifier: Programming Language :: Python :: 3
Classifier: Programming Language :: Python :: 3.10
Classifier: Programming Language :: Python :: 3.11
Requires-Dist: matplotlib (>=3.7.1,<4.0.0)
Requires-Dist: numpy (>=1.24.3,<2.0.0)
Requires-Dist: pyqt5 (>=5.15.9,<6.0.0)
Requires-Dist: scipy (>=1.10.1,<2.0.0)
Requires-Dist: seaborn (>=0.12.2,<0.13.0)
